yaqd_lightcon/VERSION
yaqd_lightcon/__init__.py
yaqd_lightcon/__version__.py
yaqd_lightcon/_lightcon_topas4_motor.py
yaqd_lightcon/_lightcon_topas4_shutter.py
yaqd_lightcon/lightcon-topas4-motor.avpr
yaqd_lightcon/lightcon-topas4-motor.toml
yaqd_lightcon/lightcon-topas4-shutter.avpr
yaqd_lightcon/lightcon-topas4-shutter.toml
yaqd_lightcon-2022.11.0.dist-info/entry_points.txt
yaqd_lightcon-2022.11.0.dist-info/LICENSE
yaqd_lightcon-2022.11.0.dist-info/WHEEL
yaqd_lightcon-2022.11.0.dist-info/METADATA
yaqd_lightcon-2022.11.0.dist-info/RECORD
