Metadata-Version: 2.1
Name: yaqd-lightcon
Version: 2022.11.0
Summary: yaq daemons for hardware from Light Conversion
Home-page: https://yaq.fyi
Author: yaq developers
Requires-Python: >=3.7
Classifier: Development Status :: 4 - Beta
Classifier: Intended Audience :: Science/Research
Classifier: License :: OSI Approved :: GNU Lesser General Public License v3 (LGPLv3)
Classifier: Natural Language :: English
Classifier: Programming Language :: Python :: 3
Classifier: Programming Language :: Python :: 3.7
Classifier: Programming Language :: Python :: 3.8
Classifier: Topic :: Scientific/Engineering
Requires-Dist: yaqd-core>=2020.10.1
Requires-Dist: aiohttp
Requires-Dist: black ; extra == "dev"
Requires-Dist: pre-commit ; extra == "dev"
Project-URL: Issues, https://github.com/yaq-project/yaqd-lightcon/issues
Project-URL: Source, https://github.com/yaq-project/yaqd-lightcon
Provides-Extra: dev
